astrea.cpython-313-x86_64-linux-gnu.so
astrea-0.8.0.dist-info/METADATA
astrea-0.8.0.dist-info/WHEEL
astrea-0.8.0.dist-info/top_level.txt
astrea-0.8.0.dist-info/RECORD
astrea-0.8.0.dist-info/licenses/LICENSE
