Metadata-Version: 2.4
Name: astrea
Version: 0.8.0
Summary: Python bindings for astrea C++ library
Author-email: Artem Shepelin <4.shepelin@gmail.com>
License: GPL-3
Keywords: physics,astronomy,astrophysics,plasma
Requires-Python: <3.15,>=3.10
License-File: LICENSE
Requires-Dist: numpy>=1.25.0
Dynamic: license-file
